ntk/__init__.py
ntk/arrow.png
ntk/icon.ico
ntk/icon.xbm
ntk/db/__init__.py
ntk/db/conn.py
ntk/db/models.py
ntk/objects/__init__.py
ntk/objects/basev.py
ntk/objects/gv.py
ntk/utils/__init__.py
ntk/utils/admin.py
ntk/utils/util.py
ntk/widgets/__init__.py
ntk/widgets/button.py
ntk/widgets/canvas.py
ntk/widgets/combo.py
ntk/widgets/entry.py
ntk/widgets/frame.py
ntk/widgets/image.py
ntk/widgets/label.py
ntk/widgets/notebook.py
ntk/widgets/panedwindow.py
ntk/widgets/radio.py
ntk/widgets/scroller.py
ntk/widgets/select.py
ntk/widgets/text.py
ntk/widgets/tk.py
ntk/widgets/toplevel.py
ntk/widgets/widgets.py
ntk-1.1.3.dist-info/LICENSE
ntk-1.1.3.dist-info/METADATA
ntk-1.1.3.dist-info/WHEEL
ntk-1.1.3.dist-info/top_level.txt
ntk-1.1.3.dist-info/RECORD
