Metadata-Version: 2.1
Name: ntk
Version: 1.1.3
Summary: NTK is set of widgets and utils that implement high-level APIs.
Home-page: https://github.com/njnafir/ntk
Author: Nj Nafir
Author-email: njnafir@gmail.com
License: MIT
Platform: UNKNOWN
Classifier: License :: OSI Approved :: MIT License
Classifier: Programming Language :: Python :: 3
Classifier: Programming Language :: Python :: 3.9
